depo/__init__.py
depo/error.py
depo/resource.py
depo/utils.py
depo/version.py
depo-0.2.0.dist-info/LICENSE
depo-0.2.0.dist-info/METADATA
depo-0.2.0.dist-info/WHEEL
depo-0.2.0.dist-info/top_level.txt
depo-0.2.0.dist-info/RECORD
